{
    "first_paragraph": "The Babadook is a 2014 Australian psychological horror film written and directed by Jennifer Kent in her feature directorial debut,[4] and produced by Kristina Ceyton and Kristian Moliere. The film stars Essie Davis, Noah Wiseman, Daniel Henshall, Hayley McElhinney, Barbara West, and Ben Winspear. Based on Kent's 2005 short film Monster, the film follows a widowed single mother who must confront her son's fear of a mysterious monster in their home.",
    "infobox": {
        "Directed by": "Jennifer Kent",
        "Screenplay by": "Jennifer Kent",
        "Based on": "Monster\nby Jennifer Kent",
        "Produced by": [
            "Kristina Ceyton",
            "Kristian Moliere"
        ],
        "Starring": [
            "Essie Davis",
            "Noah Wiseman",
            "Hayley McElhinney",
            "Daniel Henshall",
            "Barbara West",
            "Ben Winspear"
        ],
        "Cinematography": "Radek \u0141adczuk",
        "Edited by": "Simon Njoo",
        "Music by": "Jed Kurzel",
        "Production\ncompanies": [
            "Screen Australia",
            "Causeway Films",
            "South Australian Film Corporation",
            "Smoking Gun Productions",
            "Entertainment One"
        ],
        "Distributed by": "Umbrella Entertainment",
        "Release dates": [
            "17\u00a0January\u00a02014 (Sundance)",
            "22\u00a0May\u00a02014 (Australia)"
        ],
        "Running time": "94 minutes[1]",
        "Country": "Australia",
        "Language": "English",
        "Budget": "$2 million[2]",
        "Box office": "$10.5 million[3]"
    }
}